{
  "opinion": 0.10847892676802584,
  "confidence": 0.591127,
  "reasoning": "I'm neutral because I this policy helps people like me.",
  "breakdown": {
    "economicScore": 0.2984881050862593,
    "socialScore": 0.30589999999999995,
    "convenienceScore": 0.11699999999999999,
    "healthEnvScore": 0,
    "relevance": 0.5806349999999999,
    "weights": {
      "economic": 0.65,
      "social": 0.2,
      "convenience": 0.1,
      "healthEnv": 0.05
    }
  },
  "decision": "SUPPORT",
  "metadata": {
    "policy": "Bus Fare Hike",
    "domain": "transport",
    "timestamp": "2025-12-09T06:18:37.721Z",
    "humanId": "HUM_UP_Mirzapur_48"
  },
  "humanId": "HUM_UP_Mirzapur_48",
  "state": "UP"
}