{
  "opinion": 0.20657937600000004,
  "confidence": 0.65738,
  "reasoning": "I support this because I would benefit financially from this policy and I this policy helps people like me.",
  "breakdown": {
    "economicScore": 1,
    "socialScore": 0.41900000000000004,
    "convenienceScore": 0,
    "healthEnvScore": 0,
    "relevance": 0.35190000000000005,
    "weights": {
      "economic": 0.65,
      "social": 0.2,
      "convenience": 0.1,
      "healthEnv": 0.05
    }
  },
  "decision": "SUPPORT",
  "metadata": {
    "policy": "Bus Fare Hike",
    "domain": "transport",
    "timestamp": "2025-12-09T06:18:35.422Z",
    "humanId": "HUM_Maharastra_Konkan_110"
  },
  "humanId": "HUM_Maharastra_Konkan_110",
  "state": "Maharastra"
}