{
  "opinion": 0.1376934520664503,
  "confidence": 0.6806300000000001,
  "reasoning": "I'm neutral because I would benefit financially from this policy and I this policy helps people like me.",
  "breakdown": {
    "economicScore": 0.3352866755410047,
    "socialScore": 0.42000000000000004,
    "convenienceScore": 0.1495,
    "healthEnvScore": 0,
    "relevance": 0.54315,
    "weights": {
      "economic": 0.65,
      "social": 0.2,
      "convenience": 0.1,
      "healthEnv": 0.05
    }
  },
  "decision": "SUPPORT",
  "metadata": {
    "policy": "Bus Fare Hike",
    "domain": "transport",
    "timestamp": "2025-12-09T06:18:33.724Z",
    "humanId": "HUM_Delhi_South East Delhi_4"
  },
  "humanId": "HUM_Delhi_South East Delhi_4",
  "state": "Delhi"
}